greentea/__init__.py
greentea/first_class_collection.py
greentea/log.py
greentea/primitive.py
greentea/text.py
greentea/trace.py
greentea/typevar.py
greentea-3.8.0.dist-info/LICENSE
greentea-3.8.0.dist-info/METADATA
greentea-3.8.0.dist-info/WHEEL
greentea-3.8.0.dist-info/top_level.txt
greentea-3.8.0.dist-info/RECORD
