Metadata-Version: 2.1
Name: greentea
Version: 3.8.0
Summary: A microframework for abstraction.
Home-page: https://github.com/nryotaro/greentea
Author: Nakamura, Ryotaro
Author-email: nakamura.ryotaro.kzs@gmail.com
License: MIT License
Platform: UNKNOWN
Classifier: Programming Language :: Python :: 3.7
Requires-Python: >=3.7.0
Provides-Extra: dev
Requires-Dist: ipython ; extra == 'dev'
Requires-Dist: python-language-server[all] ; extra == 'dev'
Provides-Extra: doc
Requires-Dist: sphinx ; extra == 'doc'
Requires-Dist: sphinx-rtd-theme ; extra == 'doc'
Provides-Extra: test
Requires-Dist: pytest ; extra == 'test'
